amirkabirtsa/__init__.py
amirkabirtsa/adder.py
amirkabirtsa/user.py
amirkabirtsa-0.0.4.dist-info/LICENCE
amirkabirtsa-0.0.4.dist-info/METADATA
amirkabirtsa-0.0.4.dist-info/WHEEL
amirkabirtsa-0.0.4.dist-info/top_level.txt
amirkabirtsa-0.0.4.dist-info/RECORD
