Metadata-Version: 2.1
Name: amirkabirtsa
Version: 0.0.4
Summary: TSA Students Projects
Home-page: https://RacinSoft@dev.azure.com/RacinSoft/TSALibraries/_git/TSALibraries
Author: Masoud Ghasemi
Author-email: masoud.aut.ac@gmail.com
License: UNKNOWN
Download-URL: https://RacinSoft@dev.azure.com/RacinSoft/TSALibraries/_git/TSALibraries
Platform: UNKNOWN
Classifier: Programming Language :: Python :: 3
Classifier: License :: OSI Approved :: MIT License
Classifier: Operating System :: OS Independent
Requires-Python: >=3.6
